responsibleai_vision/__init__.py
responsibleai_vision/version.py
responsibleai_vision/common/__init__.py
responsibleai_vision/common/constants.py
responsibleai_vision/common/interfaces.py
responsibleai_vision/managers/__init__.py
responsibleai_vision/managers/error_analysis_manager.py
responsibleai_vision/managers/explainer_manager.py
responsibleai_vision/rai_vision_insights/__init__.py
responsibleai_vision/rai_vision_insights/rai_vision_insights.py
responsibleai_vision/utils/__init__.py
responsibleai_vision/utils/feature_extractors.py
responsibleai_vision/utils/image_reader.py
responsibleai_vision/utils/image_utils.py
responsibleai_vision-0.3.8.dist-info/METADATA
responsibleai_vision-0.3.8.dist-info/WHEEL
responsibleai_vision-0.3.8.dist-info/top_level.txt
responsibleai_vision-0.3.8.dist-info/RECORD
